package bo.com.erp360.report;

import javax.inject.Inject;
import javax.persistence.EntityManager;
import javax.servlet.annotation.WebServlet;
import javax.servlet.http.HttpServlet;

@WebServlet({"/ReportEstadoCuentasExcel"})
public class ReportEstadoCuentasExcel
  extends HttpServlet
{
  private static final long serialVersionUID = -4777861118160332227L;
  @Inject
  private EntityManager em;
  
  /* Error */
  protected void doGet(javax.servlet.http.HttpServletRequest request, javax.servlet.http.HttpServletResponse response)
    throws javax.servlet.ServletException, java.io.IOException
  {
    // Byte code:
    //   0: aload_2
    //   1: invokeinterface 30 1 0
    //   6: astore_3
    //   7: aconst_null
    //   8: astore 4
    //   10: aconst_null
    //   11: astore 7
    //   13: aconst_null
    //   14: astore 8
    //   16: new 36	javax/naming/InitialContext
    //   19: dup
    //   20: invokespecial 38	javax/naming/InitialContext:<init>	()V
    //   23: astore 9
    //   25: aload 9
    //   27: getstatic 39	bo/com/erp360/util/Conexion:datasourse	Ljava/lang/String;
    //   30: invokeinterface 45 2 0
    //   35: checkcast 51	javax/sql/DataSource
    //   38: astore 10
    //   40: aload 10
    //   42: invokeinterface 53 1 0
    //   47: astore 4
    //   49: aload 4
    //   51: ifnull +14 -> 65
    //   54: getstatic 57	java/lang/System:out	Ljava/io/PrintStream;
    //   57: ldc 63
    //   59: invokevirtual 65	java/io/PrintStream:println	(Ljava/lang/String;)V
    //   62: goto +42 -> 104
    //   65: getstatic 57	java/lang/System:out	Ljava/io/PrintStream;
    //   68: ldc 71
    //   70: invokevirtual 65	java/io/PrintStream:println	(Ljava/lang/String;)V
    //   73: goto +31 -> 104
    //   76: astore 9
    //   78: getstatic 57	java/lang/System:out	Ljava/io/PrintStream;
    //   81: new 73	java/lang/StringBuilder
    //   84: dup
    //   85: ldc 75
    //   87: invokespecial 77	java/lang/StringBuilder:<init>	(Ljava/lang/String;)V
    //   90: aload 9
    //   92: invokevirtual 79	java/lang/Exception:getMessage	()Ljava/lang/String;
    //   95: invokevirtual 85	java/lang/StringBuilder:append	(Ljava/lang/String;)Ljava/lang/StringBuilder;
    //   98: invokevirtual 89	java/lang/StringBuilder:toString	()Ljava/lang/String;
    //   101: invokevirtual 65	java/io/PrintStream:println	(Ljava/lang/String;)V
    //   104: aload_1
    //   105: ldc 92
    //   107: invokeinterface 94 2 0
    //   112: invokestatic 100	java/lang/Integer:parseInt	(Ljava/lang/String;)I
    //   115: invokestatic 106	java/lang/Integer:valueOf	(I)Ljava/lang/Integer;
    //   118: astore 9
    //   120: aload_1
    //   121: ldc 110
    //   123: invokeinterface 94 2 0
    //   128: invokestatic 100	java/lang/Integer:parseInt	(Ljava/lang/String;)I
    //   131: invokestatic 106	java/lang/Integer:valueOf	(I)Ljava/lang/Integer;
    //   134: astore 10
    //   136: aload_1
    //   137: ldc 112
    //   139: invokeinterface 94 2 0
    //   144: astore 11
    //   146: aload_1
    //   147: ldc 114
    //   149: invokeinterface 94 2 0
    //   154: invokestatic 100	java/lang/Integer:parseInt	(Ljava/lang/String;)I
    //   157: invokestatic 106	java/lang/Integer:valueOf	(I)Ljava/lang/Integer;
    //   160: astore 12
    //   162: aload_1
    //   163: ldc 116
    //   165: invokeinterface 94 2 0
    //   170: invokestatic 100	java/lang/Integer:parseInt	(Ljava/lang/String;)I
    //   173: invokestatic 106	java/lang/Integer:valueOf	(I)Ljava/lang/Integer;
    //   176: astore 13
    //   178: aload_1
    //   179: ldc 118
    //   181: invokeinterface 94 2 0
    //   186: astore 14
    //   188: aload_1
    //   189: ldc 120
    //   191: invokeinterface 94 2 0
    //   196: astore 15
    //   198: getstatic 57	java/lang/System:out	Ljava/io/PrintStream;
    //   201: new 73	java/lang/StringBuilder
    //   204: dup
    //   205: ldc 122
    //   207: invokespecial 77	java/lang/StringBuilder:<init>	(Ljava/lang/String;)V
    //   210: aload_0
    //   211: getfield 124	bo/com/erp360/report/ReportEstadoCuentasExcel:em	Ljavax/persistence/EntityManager;
    //   214: invokeinterface 126 1 0
    //   219: invokevirtual 132	java/lang/StringBuilder:append	(Z)Ljava/lang/StringBuilder;
    //   222: invokevirtual 89	java/lang/StringBuilder:toString	()Ljava/lang/String;
    //   225: invokevirtual 65	java/io/PrintStream:println	(Ljava/lang/String;)V
    //   228: aload_1
    //   229: ldc -121
    //   231: invokeinterface 137 2 0
    //   236: astore 16
    //   238: getstatic 57	java/lang/System:out	Ljava/io/PrintStream;
    //   241: new 73	java/lang/StringBuilder
    //   244: dup
    //   245: ldc -116
    //   247: invokespecial 77	java/lang/StringBuilder:<init>	(Ljava/lang/String;)V
    //   250: aload 16
    //   252: invokevirtual 85	java/lang/StringBuilder:append	(Ljava/lang/String;)Ljava/lang/StringBuilder;
    //   255: invokevirtual 89	java/lang/StringBuilder:toString	()Ljava/lang/String;
    //   258: invokevirtual 65	java/io/PrintStream:println	(Ljava/lang/String;)V
    //   261: getstatic 57	java/lang/System:out	Ljava/io/PrintStream;
    //   264: new 73	java/lang/StringBuilder
    //   267: dup
    //   268: ldc -114
    //   270: invokespecial 77	java/lang/StringBuilder:<init>	(Ljava/lang/String;)V
    //   273: aload_1
    //   274: invokeinterface 144 1 0
    //   279: invokeinterface 148 1 0
    //   284: invokevirtual 85	java/lang/StringBuilder:append	(Ljava/lang/String;)Ljava/lang/StringBuilder;
    //   287: invokevirtual 89	java/lang/StringBuilder:toString	()Ljava/lang/String;
    //   290: invokevirtual 65	java/io/PrintStream:println	(Ljava/lang/String;)V
    //   293: getstatic 57	java/lang/System:out	Ljava/io/PrintStream;
    //   296: new 73	java/lang/StringBuilder
    //   299: dup
    //   300: ldc -103
    //   302: invokespecial 77	java/lang/StringBuilder:<init>	(Ljava/lang/String;)V
    //   305: aload_1
    //   306: invokeinterface 155 1 0
    //   311: invokevirtual 85	java/lang/StringBuilder:append	(Ljava/lang/String;)Ljava/lang/StringBuilder;
    //   314: invokevirtual 89	java/lang/StringBuilder:toString	()Ljava/lang/String;
    //   317: invokevirtual 65	java/io/PrintStream:println	(Ljava/lang/String;)V
    //   320: getstatic 57	java/lang/System:out	Ljava/io/PrintStream;
    //   323: new 73	java/lang/StringBuilder
    //   326: dup
    //   327: ldc -98
    //   329: invokespecial 77	java/lang/StringBuilder:<init>	(Ljava/lang/String;)V
    //   332: aload_1
    //   333: invokeinterface 160 1 0
    //   338: invokeinterface 164 1 0
    //   343: ldc -121
    //   345: invokeinterface 167 2 0
    //   350: invokevirtual 85	java/lang/StringBuilder:append	(Ljava/lang/String;)Ljava/lang/StringBuilder;
    //   353: invokevirtual 89	java/lang/StringBuilder:toString	()Ljava/lang/String;
    //   356: invokevirtual 65	java/io/PrintStream:println	(Ljava/lang/String;)V
    //   359: aload_1
    //   360: invokeinterface 168 1 0
    //   365: invokevirtual 172	java/lang/StringBuffer:toString	()Ljava/lang/String;
    //   368: astore 17
    //   370: new 73	java/lang/StringBuilder
    //   373: dup
    //   374: aload 17
    //   376: iconst_0
    //   377: aload 17
    //   379: invokevirtual 175	java/lang/String:length	()I
    //   382: aload_1
    //   383: invokeinterface 181 1 0
    //   388: invokevirtual 175	java/lang/String:length	()I
    //   391: isub
    //   392: invokevirtual 184	java/lang/String:substring	(II)Ljava/lang/String;
    //   395: invokestatic 188	java/lang/String:valueOf	(Ljava/lang/Object;)Ljava/lang/String;
    //   398: invokespecial 77	java/lang/StringBuilder:<init>	(Ljava/lang/String;)V
    //   401: aload_1
    //   402: invokeinterface 191 1 0
    //   407: invokevirtual 85	java/lang/StringBuilder:append	(Ljava/lang/String;)Ljava/lang/StringBuilder;
    //   410: ldc -121
    //   412: invokevirtual 85	java/lang/StringBuilder:append	(Ljava/lang/String;)Ljava/lang/StringBuilder;
    //   415: invokevirtual 89	java/lang/StringBuilder:toString	()Ljava/lang/String;
    //   418: astore 17
    //   420: getstatic 57	java/lang/System:out	Ljava/io/PrintStream;
    //   423: new 73	java/lang/StringBuilder
    //   426: dup
    //   427: ldc -64
    //   429: invokespecial 77	java/lang/StringBuilder:<init>	(Ljava/lang/String;)V
    //   432: aload 17
    //   434: invokevirtual 85	java/lang/StringBuilder:append	(Ljava/lang/String;)Ljava/lang/StringBuilder;
    //   437: invokevirtual 89	java/lang/StringBuilder:toString	()Ljava/lang/String;
    //   440: invokevirtual 65	java/io/PrintStream:println	(Ljava/lang/String;)V
    //   443: new 73	java/lang/StringBuilder
    //   446: dup
    //   447: aload 17
    //   449: invokestatic 188	java/lang/String:valueOf	(Ljava/lang/Object;)Ljava/lang/String;
    //   452: invokespecial 77	java/lang/StringBuilder:<init>	(Ljava/lang/String;)V
    //   455: ldc -62
    //   457: invokevirtual 85	java/lang/StringBuilder:append	(Ljava/lang/String;)Ljava/lang/StringBuilder;
    //   460: iconst_1
    //   461: invokevirtual 196	java/lang/StringBuilder:append	(I)Ljava/lang/StringBuilder;
    //   464: ldc -57
    //   466: invokevirtual 85	java/lang/StringBuilder:append	(Ljava/lang/String;)Ljava/lang/StringBuilder;
    //   469: invokevirtual 89	java/lang/StringBuilder:toString	()Ljava/lang/String;
    //   472: astore 18
    //   474: getstatic 57	java/lang/System:out	Ljava/io/PrintStream;
    //   477: new 73	java/lang/StringBuilder
    //   480: dup
    //   481: ldc -55
    //   483: invokespecial 77	java/lang/StringBuilder:<init>	(Ljava/lang/String;)V
    //   486: aload 18
    //   488: invokevirtual 85	java/lang/StringBuilder:append	(Ljava/lang/String;)Ljava/lang/StringBuilder;
    //   491: invokevirtual 89	java/lang/StringBuilder:toString	()Ljava/lang/String;
    //   494: invokevirtual 65	java/io/PrintStream:println	(Ljava/lang/String;)V
    //   497: new 203	java/util/HashMap
    //   500: dup
    //   501: invokespecial 205	java/util/HashMap:<init>	()V
    //   504: astore 19
    //   506: aload 19
    //   508: ldc -50
    //   510: aload 9
    //   512: invokeinterface 208 3 0
    //   517: pop
    //   518: aload 19
    //   520: ldc -42
    //   522: aload 10
    //   524: invokeinterface 208 3 0
    //   529: pop
    //   530: aload 19
    //   532: ldc -40
    //   534: aload 11
    //   536: invokeinterface 208 3 0
    //   541: pop
    //   542: aload 19
    //   544: ldc -38
    //   546: aload 13
    //   548: invokeinterface 208 3 0
    //   553: pop
    //   554: aload 19
    //   556: ldc -36
    //   558: aload 15
    //   560: invokeinterface 208 3 0
    //   565: pop
    //   566: aload 19
    //   568: ldc -34
    //   570: aload 12
    //   572: invokeinterface 208 3 0
    //   577: pop
    //   578: aload 19
    //   580: ldc -32
    //   582: aload 14
    //   584: invokeinterface 208 3 0
    //   589: pop
    //   590: new 73	java/lang/StringBuilder
    //   593: dup
    //   594: aload 17
    //   596: invokestatic 188	java/lang/String:valueOf	(Ljava/lang/Object;)Ljava/lang/String;
    //   599: invokespecial 77	java/lang/StringBuilder:<init>	(Ljava/lang/String;)V
    //   602: ldc -30
    //   604: invokevirtual 85	java/lang/StringBuilder:append	(Ljava/lang/String;)Ljava/lang/StringBuilder;
    //   607: invokevirtual 89	java/lang/StringBuilder:toString	()Ljava/lang/String;
    //   610: astore 20
    //   612: getstatic 57	java/lang/System:out	Ljava/io/PrintStream;
    //   615: new 73	java/lang/StringBuilder
    //   618: dup
    //   619: ldc -28
    //   621: invokespecial 77	java/lang/StringBuilder:<init>	(Ljava/lang/String;)V
    //   624: aload 19
    //   626: invokevirtual 230	java/lang/Object:toString	()Ljava/lang/String;
    //   629: invokevirtual 85	java/lang/StringBuilder:append	(Ljava/lang/String;)Ljava/lang/StringBuilder;
    //   632: invokevirtual 89	java/lang/StringBuilder:toString	()Ljava/lang/String;
    //   635: invokevirtual 65	java/io/PrintStream:println	(Ljava/lang/String;)V
    //   638: getstatic 57	java/lang/System:out	Ljava/io/PrintStream;
    //   641: new 73	java/lang/StringBuilder
    //   644: dup
    //   645: ldc -23
    //   647: invokespecial 77	java/lang/StringBuilder:<init>	(Ljava/lang/String;)V
    //   650: aload 20
    //   652: invokevirtual 85	java/lang/StringBuilder:append	(Ljava/lang/String;)Ljava/lang/StringBuilder;
    //   655: invokevirtual 89	java/lang/StringBuilder:toString	()Ljava/lang/String;
    //   658: invokevirtual 65	java/io/PrintStream:println	(Ljava/lang/String;)V
    //   661: new 235	java/net/URL
    //   664: dup
    //   665: aload 20
    //   667: invokespecial 237	java/net/URL:<init>	(Ljava/lang/String;)V
    //   670: invokestatic 238	net/sf/jasperreports/engine/util/JRLoader:loadObject	(Ljava/net/URL;)Ljava/lang/Object;
    //   673: checkcast 244	net/sf/jasperreports/engine/JasperReport
    //   676: astore 5
    //   678: aload 5
    //   680: aload 19
    //   682: aload 4
    //   684: invokestatic 246	net/sf/jasperreports/engine/JasperFillManager:fillReport	(Lnet/sf/jasperreports/engine/JasperReport;Ljava/util/Map;Ljava/sql/Connection;)Lnet/sf/jasperreports/engine/JasperPrint;
    //   687: astore 6
    //   689: new 252	java/io/ByteArrayOutputStream
    //   692: dup
    //   693: invokespecial 254	java/io/ByteArrayOutputStream:<init>	()V
    //   696: astore 21
    //   698: new 255	net/sf/jasperreports/engine/export/JRXlsExporter
    //   701: dup
    //   702: invokespecial 257	net/sf/jasperreports/engine/export/JRXlsExporter:<init>	()V
    //   705: astore 22
    //   707: aload 22
    //   709: getstatic 258	net/sf/jasperreports/engine/export/JRXlsExporterParameter:IS_FONT_SIZE_FIX_ENABLED	Lnet/sf/jasperreports/engine/export/JRXlsAbstractExporterParameter;
    //   712: getstatic 264	java/lang/Boolean:TRUE	Ljava/lang/Boolean;
    //   715: invokevirtual 270	net/sf/jasperreports/engine/export/JRXlsExporter:setParameter	(Lnet/sf/jasperreports/engine/JRExporterParameter;Ljava/lang/Object;)V
    //   718: aload 22
    //   720: getstatic 274	net/sf/jasperreports/engine/export/JRXlsExporterParameter:JASPER_PRINT	Lnet/sf/jasperreports/engine/JRExporterParameter;
    //   723: aload 6
    //   725: invokevirtual 270	net/sf/jasperreports/engine/export/JRXlsExporter:setParameter	(Lnet/sf/jasperreports/engine/JRExporterParameter;Ljava/lang/Object;)V
    //   728: aload 22
    //   730: getstatic 278	net/sf/jasperreports/engine/export/JRXlsExporterParameter:IS_DETECT_CELL_TYPE	Lnet/sf/jasperreports/engine/export/JRXlsAbstractExporterParameter;
    //   733: getstatic 264	java/lang/Boolean:TRUE	Ljava/lang/Boolean;
    //   736: invokevirtual 270	net/sf/jasperreports/engine/export/JRXlsExporter:setParameter	(Lnet/sf/jasperreports/engine/JRExporterParameter;Ljava/lang/Object;)V
    //   739: aload 22
    //   741: getstatic 281	net/sf/jasperreports/engine/export/JRXlsExporterParameter:IS_WHITE_PAGE_BACKGROUND	Lnet/sf/jasperreports/engine/export/JRXlsAbstractExporterParameter;
    //   744: getstatic 284	java/lang/Boolean:FALSE	Ljava/lang/Boolean;
    //   747: invokevirtual 270	net/sf/jasperreports/engine/export/JRXlsExporter:setParameter	(Lnet/sf/jasperreports/engine/JRExporterParameter;Ljava/lang/Object;)V
    //   750: aload 22
    //   752: getstatic 287	net/sf/jasperreports/engine/export/JRXlsExporterParameter:IS_REMOVE_EMPTY_SPACE_BETWEEN_ROWS	Lnet/sf/jasperreports/engine/export/JRXlsAbstractExporterParameter;
    //   755: getstatic 264	java/lang/Boolean:TRUE	Ljava/lang/Boolean;
    //   758: invokevirtual 270	net/sf/jasperreports/engine/export/JRXlsExporter:setParameter	(Lnet/sf/jasperreports/engine/JRExporterParameter;Ljava/lang/Object;)V
    //   761: aload 22
    //   763: getstatic 290	net/sf/jasperreports/engine/export/JRXlsExporterParameter:IS_REMOVE_EMPTY_SPACE_BETWEEN_COLUMNS	Lnet/sf/jasperreports/engine/export/JRXlsAbstractExporterParameter;
    //   766: getstatic 264	java/lang/Boolean:TRUE	Ljava/lang/Boolean;
    //   769: invokevirtual 270	net/sf/jasperreports/engine/export/JRXlsExporter:setParameter	(Lnet/sf/jasperreports/engine/JRExporterParameter;Ljava/lang/Object;)V
    //   772: aload 22
    //   774: getstatic 293	net/sf/jasperreports/engine/export/JRXlsExporterParameter:IS_COLLAPSE_ROW_SPAN	Lnet/sf/jasperreports/engine/export/JRXlsAbstractExporterParameter;
    //   777: getstatic 264	java/lang/Boolean:TRUE	Ljava/lang/Boolean;
    //   780: invokevirtual 270	net/sf/jasperreports/engine/export/JRXlsExporter:setParameter	(Lnet/sf/jasperreports/engine/JRExporterParameter;Ljava/lang/Object;)V
    //   783: aload 22
    //   785: getstatic 296	net/sf/jasperreports/engine/export/JRXlsExporterParameter:IGNORE_PAGE_MARGINS	Lnet/sf/jasperreports/engine/JRExporterParameter;
    //   788: getstatic 264	java/lang/Boolean:TRUE	Ljava/lang/Boolean;
    //   791: invokevirtual 270	net/sf/jasperreports/engine/export/JRXlsExporter:setParameter	(Lnet/sf/jasperreports/engine/JRExporterParameter;Ljava/lang/Object;)V
    //   794: aload 22
    //   796: getstatic 299	net/sf/jasperreports/engine/export/JRXlsExporterParameter:IS_ONE_PAGE_PER_SHEET	Lnet/sf/jasperreports/engine/export/JRXlsAbstractExporterParameter;
    //   799: getstatic 284	java/lang/Boolean:FALSE	Ljava/lang/Boolean;
    //   802: invokevirtual 270	net/sf/jasperreports/engine/export/JRXlsExporter:setParameter	(Lnet/sf/jasperreports/engine/JRExporterParameter;Ljava/lang/Object;)V
    //   805: aload 22
    //   807: getstatic 302	net/sf/jasperreports/engine/export/JRXlsExporterParameter:OUTPUT_STREAM	Lnet/sf/jasperreports/engine/JRExporterParameter;
    //   810: aload 21
    //   812: invokevirtual 270	net/sf/jasperreports/engine/export/JRXlsExporter:setParameter	(Lnet/sf/jasperreports/engine/JRExporterParameter;Ljava/lang/Object;)V
    //   815: aload 22
    //   817: getstatic 305	net/sf/jasperreports/engine/export/JRXlsExporterParameter:IS_IGNORE_CELL_BORDER	Lnet/sf/jasperreports/engine/export/JRXlsAbstractExporterParameter;
    //   820: getstatic 264	java/lang/Boolean:TRUE	Ljava/lang/Boolean;
    //   823: invokevirtual 270	net/sf/jasperreports/engine/export/JRXlsExporter:setParameter	(Lnet/sf/jasperreports/engine/JRExporterParameter;Ljava/lang/Object;)V
    //   826: aload 22
    //   828: invokevirtual 308	net/sf/jasperreports/engine/export/JRXlsExporter:exportReport	()V
    //   831: goto +32 -> 863
    //   834: astore 23
    //   836: getstatic 57	java/lang/System:out	Ljava/io/PrintStream;
    //   839: new 73	java/lang/StringBuilder
    //   842: dup
    //   843: ldc_w 311
    //   846: invokespecial 77	java/lang/StringBuilder:<init>	(Ljava/lang/String;)V
    //   849: aload 23
    //   851: invokevirtual 313	net/sf/jasperreports/engine/JRException:getMessage	()Ljava/lang/String;
    //   854: invokevirtual 85	java/lang/StringBuilder:append	(Ljava/lang/String;)Ljava/lang/StringBuilder;
    //   857: invokevirtual 89	java/lang/StringBuilder:toString	()Ljava/lang/String;
    //   860: invokevirtual 65	java/io/PrintStream:println	(Ljava/lang/String;)V
    //   863: aload_2
    //   864: ldc_w 316
    //   867: invokeinterface 318 2 0
    //   872: aload_2
    //   873: aload 21
    //   875: invokevirtual 321	java/io/ByteArrayOutputStream:toByteArray	()[B
    //   878: arraylength
    //   879: invokeinterface 325 2 0
    //   884: aload_2
    //   885: ldc_w 329
    //   888: ldc_w 331
    //   891: invokeinterface 333 3 0
    //   896: aload_2
    //   897: invokeinterface 30 1 0
    //   902: astore_3
    //   903: aload_3
    //   904: aload 21
    //   906: invokevirtual 321	java/io/ByteArrayOutputStream:toByteArray	()[B
    //   909: invokevirtual 337	javax/servlet/ServletOutputStream:write	([B)V
    //   912: aload_3
    //   913: invokevirtual 343	javax/servlet/ServletOutputStream:flush	()V
    //   916: aload_3
    //   917: invokevirtual 346	javax/servlet/ServletOutputStream:close	()V
    //   920: aload 4
    //   922: invokeinterface 349 1 0
    //   927: goto +153 -> 1080
    //   930: astore 9
    //   932: aload 9
    //   934: invokevirtual 352	java/lang/Exception:printStackTrace	()V
    //   937: getstatic 57	java/lang/System:out	Ljava/io/PrintStream;
    //   940: new 73	java/lang/StringBuilder
    //   943: dup
    //   944: ldc_w 355
    //   947: invokespecial 77	java/lang/StringBuilder:<init>	(Ljava/lang/String;)V
    //   950: aload 9
    //   952: invokevirtual 79	java/lang/Exception:getMessage	()Ljava/lang/String;
    //   955: invokevirtual 85	java/lang/StringBuilder:append	(Ljava/lang/String;)Ljava/lang/StringBuilder;
    //   958: invokevirtual 89	java/lang/StringBuilder:toString	()Ljava/lang/String;
    //   961: invokevirtual 65	java/io/PrintStream:println	(Ljava/lang/String;)V
    //   964: new 357	java/io/StringWriter
    //   967: dup
    //   968: invokespecial 359	java/io/StringWriter:<init>	()V
    //   971: astore 10
    //   973: new 360	java/io/PrintWriter
    //   976: dup
    //   977: aload 10
    //   979: invokespecial 362	java/io/PrintWriter:<init>	(Ljava/io/Writer;)V
    //   982: astore 11
    //   984: aload 9
    //   986: aload 11
    //   988: invokevirtual 365	java/lang/Exception:printStackTrace	(Ljava/io/PrintWriter;)V
    //   991: aload_2
    //   992: ldc_w 368
    //   995: invokeinterface 318 2 0
    //   1000: aload_2
    //   1001: invokeinterface 30 1 0
    //   1006: aload 10
    //   1008: invokevirtual 370	java/io/StringWriter:toString	()Ljava/lang/String;
    //   1011: invokevirtual 371	javax/servlet/ServletOutputStream:print	(Ljava/lang/String;)V
    //   1014: goto +66 -> 1080
    //   1017: astore 24
    //   1019: aload 4
    //   1021: invokeinterface 374 1 0
    //   1026: ifne +51 -> 1077
    //   1029: getstatic 57	java/lang/System:out	Ljava/io/PrintStream;
    //   1032: ldc_w 377
    //   1035: invokevirtual 65	java/io/PrintStream:println	(Ljava/lang/String;)V
    //   1038: aload 4
    //   1040: invokeinterface 349 1 0
    //   1045: goto +32 -> 1077
    //   1048: astore 25
    //   1050: getstatic 57	java/lang/System:out	Ljava/io/PrintStream;
    //   1053: new 73	java/lang/StringBuilder
    //   1056: dup
    //   1057: ldc_w 379
    //   1060: invokespecial 77	java/lang/StringBuilder:<init>	(Ljava/lang/String;)V
    //   1063: aload 25
    //   1065: invokevirtual 79	java/lang/Exception:getMessage	()Ljava/lang/String;
    //   1068: invokevirtual 85	java/lang/StringBuilder:append	(Ljava/lang/String;)Ljava/lang/StringBuilder;
    //   1071: invokevirtual 89	java/lang/StringBuilder:toString	()Ljava/lang/String;
    //   1074: invokevirtual 65	java/io/PrintStream:println	(Ljava/lang/String;)V
    //   1077: aload 24
    //   1079: athrow
    //   1080: aload 4
    //   1082: invokeinterface 374 1 0
    //   1087: ifne +51 -> 1138
    //   1090: getstatic 57	java/lang/System:out	Ljava/io/PrintStream;
    //   1093: ldc_w 377
    //   1096: invokevirtual 65	java/io/PrintStream:println	(Ljava/lang/String;)V
    //   1099: aload 4
    //   1101: invokeinterface 349 1 0
    //   1106: goto +32 -> 1138
    //   1109: astore 25
    //   1111: getstatic 57	java/lang/System:out	Ljava/io/PrintStream;
    //   1114: new 73	java/lang/StringBuilder
    //   1117: dup
    //   1118: ldc_w 379
    //   1121: invokespecial 77	java/lang/StringBuilder:<init>	(Ljava/lang/String;)V
    //   1124: aload 25
    //   1126: invokevirtual 79	java/lang/Exception:getMessage	()Ljava/lang/String;
    //   1129: invokevirtual 85	java/lang/StringBuilder:append	(Ljava/lang/String;)Ljava/lang/StringBuilder;
    //   1132: invokevirtual 89	java/lang/StringBuilder:toString	()Ljava/lang/String;
    //   1135: invokevirtual 65	java/io/PrintStream:println	(Ljava/lang/String;)V
    //   1138: return
    // Line number table:
    //   Java source line #46	-> byte code offset #0
    //   Java source line #47	-> byte code offset #7
    //   Java source line #51	-> byte code offset #10
    //   Java source line #52	-> byte code offset #13
    //   Java source line #55	-> byte code offset #16
    //   Java source line #56	-> byte code offset #25
    //   Java source line #57	-> byte code offset #27
    //   Java source line #56	-> byte code offset #35
    //   Java source line #58	-> byte code offset #40
    //   Java source line #60	-> byte code offset #49
    //   Java source line #61	-> byte code offset #54
    //   Java source line #62	-> byte code offset #62
    //   Java source line #63	-> byte code offset #65
    //   Java source line #66	-> byte code offset #73
    //   Java source line #67	-> byte code offset #78
    //   Java source line #74	-> byte code offset #104
    //   Java source line #75	-> byte code offset #120
    //   Java source line #76	-> byte code offset #136
    //   Java source line #77	-> byte code offset #146
    //   Java source line #78	-> byte code offset #162
    //   Java source line #79	-> byte code offset #178
    //   Java source line #80	-> byte code offset #188
    //   Java source line #82	-> byte code offset #198
    //   Java source line #84	-> byte code offset #228
    //   Java source line #85	-> byte code offset #238
    //   Java source line #89	-> byte code offset #261
    //   Java source line #90	-> byte code offset #273
    //   Java source line #89	-> byte code offset #290
    //   Java source line #91	-> byte code offset #293
    //   Java source line #92	-> byte code offset #305
    //   Java source line #91	-> byte code offset #317
    //   Java source line #93	-> byte code offset #320
    //   Java source line #94	-> byte code offset #323
    //   Java source line #95	-> byte code offset #343
    //   Java source line #94	-> byte code offset #353
    //   Java source line #97	-> byte code offset #359
    //   Java source line #98	-> byte code offset #370
    //   Java source line #99	-> byte code offset #420
    //   Java source line #101	-> byte code offset #443
    //   Java source line #103	-> byte code offset #474
    //   Java source line #105	-> byte code offset #497
    //   Java source line #106	-> byte code offset #506
    //   Java source line #108	-> byte code offset #518
    //   Java source line #109	-> byte code offset #530
    //   Java source line #110	-> byte code offset #542
    //   Java source line #111	-> byte code offset #554
    //   Java source line #112	-> byte code offset #566
    //   Java source line #113	-> byte code offset #578
    //   Java source line #115	-> byte code offset #590
    //   Java source line #117	-> byte code offset #612
    //   Java source line #118	-> byte code offset #638
    //   Java source line #122	-> byte code offset #661
    //   Java source line #123	-> byte code offset #665
    //   Java source line #122	-> byte code offset #667
    //   Java source line #126	-> byte code offset #678
    //   Java source line #129	-> byte code offset #689
    //   Java source line #130	-> byte code offset #698
    //   Java source line #132	-> byte code offset #707
    //   Java source line #133	-> byte code offset #718
    //   Java source line #134	-> byte code offset #728
    //   Java source line #135	-> byte code offset #739
    //   Java source line #136	-> byte code offset #750
    //   Java source line #137	-> byte code offset #761
    //   Java source line #138	-> byte code offset #772
    //   Java source line #139	-> byte code offset #783
    //   Java source line #140	-> byte code offset #794
    //   Java source line #141	-> byte code offset #805
    //   Java source line #142	-> byte code offset #815
    //   Java source line #145	-> byte code offset #826
    //   Java source line #146	-> byte code offset #831
    //   Java source line #147	-> byte code offset #836
    //   Java source line #150	-> byte code offset #863
    //   Java source line #151	-> byte code offset #872
    //   Java source line #152	-> byte code offset #884
    //   Java source line #155	-> byte code offset #896
    //   Java source line #156	-> byte code offset #903
    //   Java source line #157	-> byte code offset #912
    //   Java source line #158	-> byte code offset #916
    //   Java source line #160	-> byte code offset #920
    //   Java source line #162	-> byte code offset #927
    //   Java source line #164	-> byte code offset #932
    //   Java source line #165	-> byte code offset #937
    //   Java source line #166	-> byte code offset #964
    //   Java source line #167	-> byte code offset #973
    //   Java source line #168	-> byte code offset #984
    //   Java source line #169	-> byte code offset #991
    //   Java source line #170	-> byte code offset #1000
    //   Java source line #172	-> byte code offset #1014
    //   Java source line #174	-> byte code offset #1019
    //   Java source line #175	-> byte code offset #1029
    //   Java source line #176	-> byte code offset #1038
    //   Java source line #178	-> byte code offset #1045
    //   Java source line #179	-> byte code offset #1050
    //   Java source line #181	-> byte code offset #1077
    //   Java source line #174	-> byte code offset #1080
    //   Java source line #175	-> byte code offset #1090
    //   Java source line #176	-> byte code offset #1099
    //   Java source line #178	-> byte code offset #1106
    //   Java source line #179	-> byte code offset #1111
    //   Java source line #183	-> byte code offset #1138
    // Local variable table:
    //   start	length	slot	name	signature
    //   0	1139	0	this	ReportEstadoCuentasExcel
    //   0	1139	1	request	javax.servlet.http.HttpServletRequest
    //   0	1139	2	response	javax.servlet.http.HttpServletResponse
    //   6	911	3	servletOutputStream	javax.servlet.ServletOutputStream
    //   8	1092	4	conn	java.sql.Connection
    //   676	3	5	jasperReport	net.sf.jasperreports.engine.JasperReport
    //   687	37	6	jasperPrint	net.sf.jasperreports.engine.JasperPrint
    //   11	3	7	stmt	java.sql.Statement
    //   14	3	8	rs	java.sql.ResultSet
    //   23	3	9	ctx	javax.naming.Context
    //   76	15	9	e	Exception
    //   118	393	9	pIdCuenta	Integer
    //   930	55	9	e	Exception
    //   38	3	10	ds	javax.sql.DataSource
    //   134	389	10	pIdEmpresa	Integer
    //   971	36	10	stringWriter	java.io.StringWriter
    //   144	391	11	pNombreEmpresa	String
    //   982	5	11	printWriter	java.io.PrintWriter
    //   160	411	12	pFechaInicio	Integer
    //   176	371	13	pFechaFin	Integer
    //   186	397	14	pFechaInicioTxt	String
    //   196	363	15	pFechaFinTxt	String
    //   236	15	16	realPath	String
    //   368	227	17	urlPath	String
    //   472	15	18	URL_SERVLET_LOGO	String
    //   504	177	19	parameters	java.util.Map
    //   610	56	20	rutaReporte	String
    //   696	209	21	byteArrayOutputStream	java.io.ByteArrayOutputStream
    //   705	122	22	exporterXLS	net.sf.jasperreports.engine.export.JRXlsExporter
    //   834	16	23	ex	net.sf.jasperreports.engine.JRException
    //   1017	61	24	localObject	Object
    //   1048	16	25	e	Exception
    //   1109	16	25	e	Exception
    // Exception table:
    //   from	to	target	type
    //   16	73	76	java/lang/Exception
    //   826	831	834	net/sf/jasperreports/engine/JRException
    //   104	927	930	java/lang/Exception
    //   104	1017	1017	finally
    //   1019	1045	1048	java/lang/Exception
    //   1080	1106	1109	java/lang/Exception
  }
}
